{
	"name": "credits",
	"events": [
		{
			"eventType": "block",
			"conditions": [
				{
					"id": "on-start-of-layout",
					"objectClass": "System",
					"sid": 230401203605121
				}
			],
			"actions": [
				{
					"callFunction": "LayoutVisualTransition",
					"sid": 715929595466133
				}
			],
			"sid": 589130570082710
		},
		{
			"eventType": "block",
			"conditions": [
				{
					"id": "on-clicked-id",
					"objectClass": "menuChoice",
					"sid": 785498999351024,
					"parameters": {
						"id": "\"menu-start\""
					}
				}
			],
			"actions": [
				{
					"callFunction": "LayoutChange",
					"sid": 702355426651033,
					"parameters": [
						"\"start\""
					]
				},
				{
					"id": "play",
					"objectClass": "Audio",
					"sid": 438352172761735,
					"parameters": {
						"audio-file": {
							"path": "button-click"
						},
						"loop": "not-looping",
						"volume": "0",
						"stereo-pan": "0",
						"tag-optional": "\"\""
					}
				}
			],
			"sid": 177671125071278
		}
	],
	"sid": 410612485855588
}